Monedas_Gonzalez_Gonzalez/__init__.py
Monedas_Gonzalez_Gonzalez/analizador.py
Monedas_Gonzalez_Gonzalez/bandas_bollinger.py
Monedas_Gonzalez_Gonzalez/main.py
Monedas_Gonzalez_Gonzalez/mostrador_datos.py
Monedas_Gonzalez_Gonzalez/obtencion_datos.py
Monedas_Gonzalez_Gonzalez-1.0.8.dist-info/METADATA
Monedas_Gonzalez_Gonzalez-1.0.8.dist-info/WHEEL
Monedas_Gonzalez_Gonzalez-1.0.8.dist-info/entry_points.txt
Monedas_Gonzalez_Gonzalez-1.0.8.dist-info/top_level.txt
Monedas_Gonzalez_Gonzalez-1.0.8.dist-info/RECORD
