Metadata-Version: 2.1
Name: Monedas_Gonzalez_Gonzalez
Version: 1.0.8
Summary: Soporte para análisis de bandas de Bollinger en criptomonedas
Home-page: https://github.com/LuisGonzalez2002/ProyectoGonzalez_Gonzalez
Author: Luis González
Author-email: lgg2002419@gmail.com
Classifier: Development Status :: 3 - Alpha
Classifier: Intended Audience :: Developers
Classifier: License :: OSI Approved :: MIT License
Classifier: Programming Language :: Python :: 3.12
Requires-Python: >=3.12
Requires-Dist: krakenex
Requires-Dist: pandas
Requires-Dist: matplotlib
